uopy/__init__.py
uopy/_command.py
uopy/_config.py
uopy/_constants.py
uopy/_dictionary.py
uopy/_dynarray.py
uopy/_errorcodes.py
uopy/_file.py
uopy/_fileinfo.py
uopy/_funccodes.py
uopy/_list.py
uopy/_logger.py
uopy/_mvdelimited.py
uopy/_nlslocale.py
uopy/_nlsmap.py
uopy/_pool.py
uopy/_recordset.py
uopy/_sequentialfile.py
uopy/_session.py
uopy/_subroutine.py
uopy/_transaction.py
uopy/_uniobject.py
uopy/_unirpc.py
uopy/_uoerror.py
uopy/_uofile_error.py
uopy/_uopy.py
uopy/_utils.py
uopy-1.4.0.dist-info/LICENSE
uopy-1.4.0.dist-info/METADATA
uopy-1.4.0.dist-info/NOTICE
uopy-1.4.0.dist-info/WHEEL
uopy-1.4.0.dist-info/top_level.txt
uopy-1.4.0.dist-info/RECORD
