Metadata-Version: 2.2
Name: uopy
Version: 1.4.0
Summary: UniObjects for Python (UOPY) is a Python package by Rocket Software.
Home-page: https://www.rocketsoftware.com/products/rocket-multivalue-application-development-platform/rocket-uopy
Author: Rocket Software
Author-email: support@rocketsoftware.com
License: Rocket Software EULA
Project-URL: Documentation, https://rocketsoftware.github.io/uopy-demo/docs/uopy.html
Project-URL: Changelog, https://github.com/RocketSoftware/uopy-demo/blob/master/CHANGELOG.md
Keywords: MultiValue,MV,uopy,database
Classifier: Development Status :: 5 - Production/Stable
Classifier: Programming Language :: Python :: 3
Classifier: Topic :: Database
Requires-Python: >=3
License-File: LICENSE
License-File: NOTICE
Dynamic: author
Dynamic: author-email
Dynamic: classifier
Dynamic: description
Dynamic: description-content-type
Dynamic: home-page
Dynamic: keywords
Dynamic: license
Dynamic: project-url
Dynamic: requires-python
Dynamic: summary
